loudhailer/__init__.py
loudhailer/backends/__init__.py
loudhailer/backends/base.py
loudhailer/backends/rabbitmq.py
loudhailer/backends/redis.py
loudhailer/backends/utils.py
loudhailer/dataclasses.py
loudhailer/ext/__init__.py
loudhailer/ext/channels.py
loudhailer/loudhailer.py
loudhailer/utils.py
loudhailer-0.3.3.dist-info/WHEEL
loudhailer-0.3.3.dist-info/LICENSE
loudhailer-0.3.3.dist-info/METADATA
loudhailer-0.3.3.dist-info/RECORD
