Metadata-Version: 2.1
Name: loudhailer
Version: 0.3.3
Summary: 
Home-page: https://connect.cloudblue.com
License: Apache-2.0
Author: CloudBlue LLC
Requires-Python: >=3.8,<4
Classifier: Development Status :: 4 - Beta
Classifier: Environment :: Web Environment
Classifier: Intended Audience :: Developers
Classifier: License :: OSI Approved :: Apache Software License
Classifier: Operating System :: OS Independent
Classifier: Programming Language :: Python :: 3
Classifier: Programming Language :: Python :: 3.8
Classifier: Programming Language :: Python :: 3.9
Classifier: Programming Language :: Python :: 3.10
Classifier: Programming Language :: Python :: 3.11
Classifier: Programming Language :: Python :: 3
Classifier: Programming Language :: Python :: 3.10
Classifier: Programming Language :: Python :: 3.8
Classifier: Programming Language :: Python :: 3.9
Classifier: Topic :: Internet :: WWW/HTTP
Classifier: Topic :: Software Development :: Libraries
Classifier: Topic :: Utilities
Provides-Extra: channels
Requires-Dist: aiormq (>=6.3.3,<7.0.0)
Requires-Dist: async-timeout (>=4.0.2,<5.0.0)
Requires-Dist: backports.zoneinfo ; python_version < "3.9"
Requires-Dist: channels (>=3.0.0,<4.0.0) ; extra == "channels"
Requires-Dist: redis (>=4.3.4,<5.0.0)
Requires-Dist: tzdata ; sys_platform == "win32"
Project-URL: Repository, https://github.com/cloudblue/loudhailer
